Workbook

Sheet Assumptions+Unit
A1: FEIERABEND — DECKE 01 · P&L MODEL
A2: Yellow cells are assumptions — edit them; everything else recalculates.
A4: ASSUMPTIONS
A5: Retail price (duties & delivery included) | B5: 589 | C5: site pricing
A6: Annual run (units) | B6: 15000 | C6: 15,000 a year — never more
A7: Return rate (30-night trial) | B7: 0.07 | C7: premium DTC bedding norm 5–10%
A8: Value recovered on returns | B8: 0.5 | C8: resold via seconds/mended channel
A9: Mill cost / unit (yarn, weave, finish, numbering) | B9: 98 | C9: ~1.6 kg merino yarn in; EU mill ex-works €70–100
A10: Packaging / unit (box, twill, seal, card, shipper) | B10: 18 | C10: rigid box ~$10 at volume
A11: Freight to US / unit (sea, consolidated) | B11: 8
A12: EU tariff on customs value | B12: 0.15 | C12: 2025 US–EU trade deal
A13: 3PL pick-pack + last-mile / unit | B13: 21 | C13: 5–6 lb dimensional box
A14: Payment processing (% of price) | B14: 0.029
A15: Return ship + handling / return | B15: 20
A16: Lifetime-mending reserve / unit | B16: 3 | C16: low redemption; brand equity
A17: Blended CAC / unit sold | B17: 120 | C17: the biggest swing — see Scenarios
A18: Team, content, tools, G&A (annual) | B18: 1100000 | C18: ~5–6 heads incl. white-glove CX
A20: UNIT ECONOMICS
A21: Landed COGS / unit | B21: =B9+B10+B11+(B9+B10)*B12 | C21: mill + packaging + freight + tariff
A22: Gross margin / unit | B22: =B5-B21
A23: Gross margin % | B23: =B22/B5 | C23: target 70–80% for premium DTC
A24: Returns cost / unit (averaged over all units) | B24: =B7*(B15+(B9+B10)*(1-B8)) | C24: ship+handling plus unrecovered product value
A25: Fulfillment + payments / unit | B25: =B13+B5*B14
A26: Contribution before marketing / unit | B26: =B5-B21-B24-B25-B16
A27: Contribution after CAC / unit | B27: =B26-B17

Sheet Annual P&L
A1: ANNUAL P&L — SELL-OUT YEAR
A3: Line | B3: $ | C3: % net rev | D3: Notes
A4: Gross revenue | B4: ='Assumptions+Unit'!B5*'Assumptions+Unit'!B6 | C4: =B4/B$6 | D4: price × units
A5: Returns & allowances | B5: =-'Assumptions+Unit'!B5*'Assumptions+Unit'!B6*'Assumptions+Unit'!B7*(1-'Assumptions+Unit'!B8) | C5: =B5/B$6 | D5: unrecovered refunds
A6: Net revenue | B6: =B4+B5 | C6: =B6/B$6
A7: COGS (landed) | B7: =-'Assumptions+Unit'!B21*'Assumptions+Unit'!B6 | C7: =B7/B$6
A8: Gross profit | B8: =B6+B7 | C8: =B8/B$6
A9: Fulfillment, payments, returns, mending | B9: =-('Assumptions+Unit'!B25+'Assumptions+Unit'!B24+'Assumptions+Unit'!B16)*'Assumptions+Unit'!B6 | C9: =B9/B$6
A10: Contribution | B10: =B8+B9 | C10: =B10/B$6
A11: Marketing | B11: =-'Assumptions+Unit'!B17*'Assumptions+Unit'!B6 | C11: =B11/B$6 | D11: blended CAC × units
A12: Team, content, tools, G&A | B12: =-'Assumptions+Unit'!B18 | C12: =B12/B$6
A13: EBITDA | B13: =B10+B11+B12 | C13: =B13/B$6

Sheet Scenarios
A1: SCENARIOS — YEAR ONE REALITY CHECK
B3: Conservative | C3: Base | D3: Sell-out
A4: Units sold | B4: 3000 | C4: 8000 | D4: 15000
A5: Blended CAC | B5: 200 | C5: 150 | D5: 120
A6: Net revenue | B6: ='Assumptions+Unit'!B5*B4*(1-'Assumptions+Unit'!B7*(1-'Assumptions+Unit'!B8)) | C6: ='Assumptions+Unit'!B5*C4*(1-'Assumptions+Unit'!B7*(1-'Assumptions+Unit'!B8)) | D6: ='Assumptions+Unit'!B5*D4*(1-'Assumptions+Unit'!B7*(1-'Assumptions+Unit'!B8))
A7: Contribution | B7: ='Assumptions+Unit'!B26*B4 | C7: ='Assumptions+Unit'!B26*C4 | D7: ='Assumptions+Unit'!B26*D4
A8: Marketing | B8: =-B5*B4 | C8: =-C5*C4 | D8: =-D5*D4
A9: Fixed OpEx | B9: =-'Assumptions+Unit'!B18 | C9: =-'Assumptions+Unit'!B18 | D9: =-'Assumptions+Unit'!B18
A10: EBITDA | B10: =B7+B8+B9 | C10: =C7+C8+C9 | D10: =D7+D8+D9
A11: EBITDA % of net | B11: =B10/B6 | C11: =C10/C6 | D11: =D10/D6
A13: Year one honestly: prove the waitlist at 3–8k units before committing the mill to 15,000.
